gnomadapi/GnomadAPI.py
gnomadapi/__init__.py
gnomadapi/__main__.py
gnomadapi-1.0.3.dist-info/entry_points.txt
gnomadapi-1.0.3.dist-info/WHEEL
gnomadapi-1.0.3.dist-info/METADATA
gnomadapi-1.0.3.dist-info/RECORD
